{"gameId": "0022401112", "gameTimeLocal": "2025-04-03T19:00:00-04:00", "gameTimeUTC": "2025-04-03T23:00:00Z", "gameTimeHome": "2025-04-03T19:00:00-04:00", "gameTimeAway": "2025-04-03T19:00:00-04:00", "gameEt": "2025-04-03T19:00:00-04:00", "duration": 136, "gameCode": "20250403/ORLWAS", "gameStatusText": "Final", "gameStatus": 3, "regulationPeriods": 4, "period": 4, "gameClock": "PT00M00.00S", "attendance": 15998, "sellout": "0", "arena": {"arenaId": 77, "arenaName": "Capital One Arena", "arenaCity": "Washington", "arenaState": "DC", "arenaCountry": "US", "arenaTimezone": "America/New_York"}, "officials": [{"personId": 1830, "name": "Marc Davis", "nameI": "M. Davis", "firstName": "Marc", "familyName": "Davis", "jerseyNum": "8", "assignment": "OFFICIAL1"}, {"personId": 202007, "name": "Nick Buchert", "nameI": "N. Buchert", "firstName": "Nick", "familyName": "Buchert", "jerseyNum": "3", "assignment": "OFFICIAL2"}, {"personId": 1630886, "name": "Intae Hwang", "nameI": "I. Hwang", "firstName": "Intae", "familyName": "Hwang", "jerseyNum": "73", "assignment": "OFFICIAL3"}], "homeTeam": {"teamId": 1610612764, "teamName": "Wizards", "teamCity": "Washington", "teamTricode": "WAS", "score": 97, "inBonus": "0", "timeoutsRemaining": 1, "periods": [{"period": 1, "periodType": "REGULAR", "score": 27}, {"period": 2, "periodType": "REGULAR", "score": 18}, {"period": 3, "periodType": "REGULAR", "score": 31}, {"period": 4, "periodType": "REGULAR", "score": 21}], "players": [{"status": "ACTIVE", "order": 1, "personId": 1630551, "jerseyNum": "9", "position": "SF", "starter": "1", "oncourt": "0", "played": "1", "statistics": {"assists": 0, "blocks": 1, "blocksReceived": 0, "fieldGoalsAttempted": 6, "fieldGoalsMade": 4, "fieldGoalsPercentage": 0.666666666666666, "foulsOffensive": 0, "foulsDrawn": 1, "foulsPersonal": 1, "foulsTechnical": 0, "freeThrowsAttempted": 0, "freeThrowsMade": 0, "freeThrowsPercentage": 0.0, "minus": 54.0, "minutes": "PT23M05.00S", "minutesCalculated": "PT23M", "plus": 57.0, "plusMinusPoints": 3.0, "points": 8, "pointsFastBreak": 2, "pointsInThePaint": 8, "pointsSecondChance": 2, "reboundsDefensive": 0, "reboundsOffensive": 1, "reboundsTotal": 1, "steals": 1, "threePointersAttempted": 2, "threePointersMade": 0, "threePointersPercentage": 0.0, "turnovers": 0, "twoPointersAttempted": 4, "twoPointersMade": 4, "twoPointersPercentage": 1.0}, "name": "Justin Champagnie", "nameI": "J. Champagnie", "firstName": "Justin", "familyName": "Champagnie"}, {"status": "ACTIVE", "order": 2, "personId": 203935, "jerseyNum": "36", "position": "PF", "starter": "1", "oncourt": "0", "played": "1", "statistics": {"assists": 0, "blocks": 0, "blocksReceived": 1, "fieldGoalsAttempted": 7, "fieldGoalsMade": 4, "fieldGoalsPercentage": 0.5714285714285711, "foulsOffensive": 0, "foulsDrawn": 2, "foulsPersonal": 0, "foulsTechnical": 0, "freeThrowsAttempted": 2, "freeThrowsMade": 2, "freeThrowsPercentage": 1.0, "minus": 51.0, "minutes": "PT24M33.00S", "minutesCalculated": "PT24M", "plus": 61.0, "plusMinusPoints": 10.0, "points": 12, "pointsFastBreak": 0, "pointsInThePaint": 2, "pointsSecondChance": 0, "reboundsDefensive": 3, "reboundsOffensive": 0, "reboundsTotal": 3, "steals": 0, "threePointersAttempted": 4, "threePointersMade": 2, "threePointersPercentage": 0.5, "turnovers": 1, "twoPointersAttempted": 3, "twoPointersMade": 2, "twoPointersPercentage": 0.666666666666666}, "name": "Marcus Smart", "nameI": "M. Smart", "firstName": "Marcus", "familyName": "Smart"}, {"status": "ACTIVE", "order": 3, "personId": 1642259, "jerseyNum": "20", "position": "C", "starter": "1", "oncourt": "0", "played": "1", "statistics": {"assists": 6, "blocks": 0, "blocksReceived": 1, "fieldGoalsAttempted": 16, "fieldGoalsMade": 4, "fieldGoalsPercentage": 0.25, "foulsOffensive": 0, "foulsDrawn": 2, "foulsPersonal": 2, "foulsTechnical": 0, "freeThrowsAttempted": 2, "freeThrowsMade": 2, "freeThrowsPercentage": 1.0, "minus": 71.0, "minutes": "PT32M05.00S", "minutesCalculated": "PT32M", "plus": 73.0, "plusMinusPoints": 2.0, "points": 10, "pointsFastBreak": 2, "pointsInThePaint": 6, "pointsSecondChance": 0, "reboundsDefensive": 5, "reboundsOffensive": 1, "reboundsTotal": 6, "steals": 1, "threePointersAttempted": 5, "threePointersMade": 0, "threePointersPercentage": 0.0, "turnovers": 3, "twoPointersAttempted": 11, "twoPointersMade": 4, "twoPointersPercentage": 0.36363636363636404}, "name": "Alex Sarr", "nameI": "A. Sarr", "firstName": "Alex", "familyName": "Sarr"}, {"status": "ACTIVE", "order": 4, "personId": 1642358, "jerseyNum": "5", "position": "SG", "starter": "1", "oncourt": "1", "played": "1", "statistics": {"assists": 2, "blocks": 1, "blocksReceived": 3, "fieldGoalsAttempted": 10, "fieldGoalsMade": 4, "fieldGoalsPercentage": 0.4, "foulsOffensive": 1, "foulsDrawn": 3, "foulsPersonal": 4, "foulsTechnical": 0, "freeThrowsAttempted": 2, "freeThrowsMade": 2, "freeThrowsPercentage": 1.0, "minus": 61.0, "minutes": "PT28M55.00S", "minutesCalculated": "PT29M", "plus": 58.0, "plusMinusPoints": -3.0, "points": 11, "pointsFastBreak": 0, "pointsInThePaint": 6, "pointsSecondChance": 0, "reboundsDefensive": 4, "reboundsOffensive": 0, "reboundsTotal": 4, "steals": 0, "threePointersAttempted": 2, "threePointersMade": 1, "threePointersPercentage": 0.5, "turnovers": 3, "twoPointersAttempted": 8, "twoPointersMade": 3, "twoPointersPercentage": 0.375}, "name": "AJ Johnson", "nameI": "A. Johnson", "firstName": "AJ", "familyName": "Johnson"}, {"status": "ACTIVE", "order": 5, "personId": 1642267, "jerseyNum": "8", "position": "PG", "starter": "1", "oncourt": "1", "played": "1", "statistics": {"assists": 7, "blocks": 0, "blocksReceived": 0, "fieldGoalsAttempted": 18, "fieldGoalsMade": 12, "fieldGoalsPercentage": 0.666666666666666, "foulsOffensive": 1, "foulsDrawn": 1, "foulsPersonal": 3, "foulsTechnical": 0, "freeThrowsAttempted": 1, "freeThrowsMade": 1, "freeThrowsPercentage": 1.0, "minus": 85.0, "minutes": "PT36M38.00S", "minutesCalculated": "PT37M", "plus": 80.0, "plusMinusPoints": -5.0, "points": 32, "pointsFastBreak": 0, "pointsInThePaint": 4, "pointsSecondChance": 5, "reboundsDefensive": 8, "reboundsOffensive": 1, "reboundsTotal": 9, "steals": 0, "threePointersAttempted": 10, "threePointersMade": 7, "threePointersPercentage": 0.7, "turnovers": 1, "twoPointersAttempted": 8, "twoPointersMade": 5, "twoPointersPercentage": 0.625}, "name": "Bub Carrington", "nameI": "B. Carrington", "firstName": "Bub", "familyName": "Carrington"}, {"status": "ACTIVE", "order": 6, "personId": 1641732, "jerseyNum": "1", "starter": "0", "oncourt": "1", "played": "1", "statistics": {"assists": 0, "blocks": 0, "blocksReceived": 1, "fieldGoalsAttempted": 8, "fieldGoalsMade": 3, "fieldGoalsPercentage": 0.375, "foulsOffensive": 0, "foulsDrawn": 1, "foulsPersonal": 4, "foulsTechnical": 0, "freeThrowsAttempted": 0, "freeThrowsMade": 0, "freeThrowsPercentage": 0.0, "minus": 87.0, "minutes": "PT36M59.00S", "minutesCalculated": "PT37M", "plus": 72.0, "plusMinusPoints": -15.0, "points": 6, "pointsFastBreak": 2, "pointsInThePaint": 6, "pointsSecondChance": 2, "reboundsDefensive": 6, "reboundsOffensive": 1, "reboundsTotal": 7, "steals": 1, "threePointersAttempted": 4, "threePointersMade": 0, "threePointersPercentage": 0.0, "turnovers": 1, "twoPointersAttempted": 4, "twoPointersMade": 3, "twoPointersPercentage": 0.75}, "name": "Colby Jones", "nameI": "C. Jones", "firstName": "Colby", "familyName": "Jones"}, {"status": "ACTIVE", "order": 7, "personId": 1641798, "jerseyNum": "4", "starter": "0", "oncourt": "1", "played": "1", "statistics": {"assists": 1, "blocks": 0, "blocksReceived": 1, "fieldGoalsAttempted": 7, "fieldGoalsMade": 2, "fieldGoalsPercentage": 0.28571428571428603, "foulsOffensive": 0, "foulsDrawn": 1, "foulsPersonal": 1, "foulsTechnical": 0, "freeThrowsAttempted": 2, "freeThrowsMade": 2, "freeThrowsPercentage": 1.0, "minus": 56.0, "minutes": "PT21M50.00S", "minutesCalculated": "PT22M", "plus": 33.0, "plusMinusPoints": -23.0, "points": 7, "pointsFastBreak": 2, "pointsInThePaint": 2, "pointsSecondChance": 0, "reboundsDefensive": 2, "reboundsOffensive": 0, "reboundsTotal": 2, "steals": 1, "threePointersAttempted": 2, "threePointersMade": 1, "threePointersPercentage": 0.5, "turnovers": 0, "twoPointersAttempted": 5, "twoPointersMade": 1, "twoPointersPercentage": 0.2}, "name": "Jaylen Martin", "nameI": "J. Martin", "firstName": "Jaylen", "familyName": "Martin"}, {"status": "ACTIVE", "order": 8, "personId": 1641774, "jerseyNum": "00", "starter": "0", "oncourt": "1", "played": "1", "statistics": {"assists": 0, "blocks": 1, "blocksReceived": 0, "fieldGoalsAttempted": 7, "fieldGoalsMade": 3, "fieldGoalsPercentage": 0.428571428571429, "foulsOffensive": 1, "foulsDrawn": 0, "foulsPersonal": 4, "foulsTechnical": 0, "freeThrowsAttempted": 0, "freeThrowsMade": 0, "freeThrowsPercentage": 0.0, "minus": 32.0, "minutes": "PT14M09.00S", "minutesCalculated": "PT14M", "plus": 20.0, "plusMinusPoints": -12.0, "points": 7, "pointsFastBreak": 0, "pointsInThePaint": 2, "pointsSecondChance": 0, "reboundsDefensive": 1, "reboundsOffensive": 0, "reboundsTotal": 1, "steals": 0, "threePointersAttempted": 1, "threePointersMade": 1, "threePointersPercentage": 1.0, "turnovers": 4, "twoPointersAttempted": 6, "twoPointersMade": 2, "twoPointersPercentage": 0.333333333333333}, "name": "Tristan Vukcevic", "nameI": "T. Vukcevic", "firstName": "Tristan", "familyName": "Vukcevic"}, {"status": "ACTIVE", "order": 9, "personId": 1630264, "jerseyNum": "16", "starter": "0", "oncourt": "0", "played": "1", "statistics": {"assists": 0, "blocks": 0, "blocksReceived": 1, "fieldGoalsAttempted": 6, "fieldGoalsMade": 2, "fieldGoalsPercentage": 0.333333333333333, "foulsOffensive": 0, "foulsDrawn": 1, "foulsPersonal": 1, "foulsTechnical": 0, "freeThrowsAttempted": 2, "freeThrowsMade": 0, "freeThrowsPercentage": 0.0, "minus": 48.0, "minutes": "PT21M46.00S", "minutesCalculated": "PT22M", "plus": 31.0, "plusMinusPoints": -17.0, "points": 4, "pointsFastBreak": 0, "pointsInThePaint": 4, "pointsSecondChance": 2, "reboundsDefensive": 1, "reboundsOffensive": 4, "reboundsTotal": 5, "steals": 0, "threePointersAttempted": 0, "threePointersMade": 0, "threePointersPercentage": 0.0, "turnovers": 0, "twoPointersAttempted": 6, "twoPointersMade": 2, "twoPointersPercentage": 0.333333333333333}, "name": "Anthony Gill", "nameI": "A. Gill", "firstName": "Anthony", "familyName": "Gill"}, {"status": "ACTIVE", "notPlayingReason": "DND_INJURY", "notPlayingDescription": "Left Ankle; Sprain", "order": 10, "personId": 1627763, "jerseyNum": "15", "starter": "0", "oncourt": "0", "played": "0", "statistics": {"assists": 0, "blocks": 0, "blocksReceived": 0, "fieldGoalsAttempted": 0, "fieldGoalsMade": 0, "fieldGoalsPercentage": 0.0, "foulsOffensive": 0, "foulsDrawn": 0, "foulsPersonal": 0, "foulsTechnical": 0, "freeThrowsAttempted": 0, "freeThrowsMade": 0, "freeThrowsPercentage": 0.0, "minus": 0.0, "minutes": "PT00M00.00S", "minutesCalculated": "PT00M", "plus": 0.0, "plusMinusPoints": 0.0, "points": 0, "pointsFastBreak": 0, "pointsInThePaint": 0, "pointsSecondChance": 0, "reboundsDefensive": 0, "reboundsOffensive": 0, "reboundsTotal": 0, "steals": 0, "threePointersAttempted": 0, "threePointersMade": 0, "threePointersPercentage": 0.0, "turnovers": 0, "twoPointersAttempted": 0, "twoPointersMade": 0, "twoPointersPercentage": 0.0}, "name": "Malcolm Brogdon", "nameI": "M. Brogdon", "firstName": "Malcolm", "familyName": "Brogdon"}, {"status": "ACTIVE", "notPlayingReason": "DND_INJURY", "notPlayingDescription": "Left Ankle; Sprain", "order": 11, "personId": 1642273, "jerseyNum": "18", "starter": "0", "oncourt": "0", "played": "0", "statistics": {"assists": 0, "blocks": 0, "blocksReceived": 0, "fieldGoalsAttempted": 0, "fieldGoalsMade": 0, "fieldGoalsPercentage": 0.0, "foulsOffensive": 0, "foulsDrawn": 0, "foulsPersonal": 0, "foulsTechnical": 0, "freeThrowsAttempted": 0, "freeThrowsMade": 0, "freeThrowsPercentage": 0.0, "minus": 0.0, "minutes": "PT00M00.00S", "minutesCalculated": "PT00M", "plus": 0.0, "plusMinusPoints": 0.0, "points": 0, "pointsFastBreak": 0, "pointsInThePaint": 0, "pointsSecondChance": 0, "reboundsDefensive": 0, "reboundsOffensive": 0, "reboundsTotal": 0, "steals": 0, "threePointersAttempted": 0, "threePointersMade": 0, "threePointersPercentage": 0.0, "turnovers": 0, "twoPointersAttempted": 0, "twoPointersMade": 0, "twoPointersPercentage": 0.0}, "name": "Kyshawn George", "nameI": "K. George", "firstName": "Kyshawn", "familyName": "George"}, {"status": "ACTIVE", "order": 12, "personId": 1630550, "jerseyNum": "21", "starter": "0", "oncourt": "0", "played": "0", "statistics": {"assists": 0, "blocks": 0, "blocksReceived": 0, "fieldGoalsAttempted": 0, "fieldGoalsMade": 0, "fieldGoalsPercentage": 0.0, "foulsOffensive": 0, "foulsDrawn": 0, "foulsPersonal": 0, "foulsTechnical": 0, "freeThrowsAttempted": 0, "freeThrowsMade": 0, "freeThrowsPercentage": 0.0, "minus": 0.0, "minutes": "PT00M00.00S", "minutesCalculated": "PT00M", "plus": 0.0, "plusMinusPoints": 0.0, "points": 0, "pointsFastBreak": 0, "pointsInThePaint": 0, "pointsSecondChance": 0, "reboundsDefensive": 0, "reboundsOffensive": 0, "reboundsTotal": 0, "steals": 0, "threePointersAttempted": 0, "threePointersMade": 0, "threePointersPercentage": 0.0, "turnovers": 0, "twoPointersAttempted": 0, "twoPointersMade": 0, "twoPointersPercentage": 0.0}, "name": "JT Thor", "nameI": "J. Thor", "firstName": "JT", "familyName": "Thor"}, {"status": "INACTIVE", "notPlayingReason": "INACTIVE_INJURY", "notPlayingDescription": "Left Knee; ACL Surgery", "order": 13, "personId": 1630180, "jerseyNum": "14", "starter": "0", "oncourt": "0", "played": "0", "statistics": {"assists": 0, "blocks": 0, "blocksReceived": 0, "fieldGoalsAttempted": 0, "fieldGoalsMade": 0, "fieldGoalsPercentage": 0.0, "foulsOffensive": 0, "foulsDrawn": 0, "foulsPersonal": 0, "foulsTechnical": 0, "freeThrowsAttempted": 0, "freeThrowsMade": 0, "freeThrowsPercentage": 0.0, "minus": 0.0, "minutes": "PT00M00.00S", "minutesCalculated": "PT00M", "plus": 0.0, "plusMinusPoints": 0.0, "points": 0, "pointsFastBreak": 0, "pointsInThePaint": 0, "pointsSecondChance": 0, "reboundsDefensive": 0, "reboundsOffensive": 0, "reboundsTotal": 0, "steals": 0, "threePointersAttempted": 0, "threePointersMade": 0, "threePointersPercentage": 0.0, "turnovers": 0, "twoPointersAttempted": 0, "twoPointersMade": 0, "twoPointersPercentage": 0.0}, "name": "Saddiq Bey", "nameI": "S. Bey", "firstName": "Saddiq", "familyName": "Bey"}, {"status": "INACTIVE", "notPlayingReason": "INACTIVE_INJURY", "notPlayingDescription": "Right Hamstring; Strain", "order": 14, "personId": 1641731, "jerseyNum": "0", "starter": "0", "oncourt": "0", "played": "0", "statistics": {"assists": 0, "blocks": 0, "blocksReceived": 0, "fieldGoalsAttempted": 0, "fieldGoalsMade": 0, "fieldGoalsPercentage": 0.0, "foulsOffensive": 0, "foulsDrawn": 0, "foulsPersonal": 0, "foulsTechnical": 0, "freeThrowsAttempted": 0, "freeThrowsMade": 0, "freeThrowsPercentage": 0.0, "minus": 0.0, "minutes": "PT00M00.00S", "minutesCalculated": "PT00M", "plus": 0.0, "plusMinusPoints": 0.0, "points": 0, "pointsFastBreak": 0, "pointsInThePaint": 0, "pointsSecondChance": 0, "reboundsDefensive": 0, "reboundsOffensive": 0, "reboundsTotal": 0, "steals": 0, "threePointersAttempted": 0, "threePointersMade": 0, "threePointersPercentage": 0.0, "turnovers": 0, "twoPointersAttempted": 0, "twoPointersMade": 0, "twoPointersPercentage": 0.0}, "name": "Bilal Coulibaly", "nameI": "B. Coulibaly", "firstName": "Bilal", "familyName": "Coulibaly"}, {"status": "INACTIVE", "notPlayingReason": "INACTIVE_INJURY", "notPlayingDescription": "Right Shoulder; Contusion", "order": 15, "personId": 1626158, "jerseyNum": "22", "starter": "0", "oncourt": "0", "played": "0", "statistics": {"assists": 0, "blocks": 0, "blocksReceived": 0, "fieldGoalsAttempted": 0, "fieldGoalsMade": 0, "fieldGoalsPercentage": 0.0, "foulsOffensive": 0, "foulsDrawn": 0, "foulsPersonal": 0, "foulsTechnical": 0, "freeThrowsAttempted": 0, "freeThrowsMade": 0, "freeThrowsPercentage": 0.0, "minus": 0.0, "minutes": "PT00M00.00S", "minutesCalculated": "PT00M", "plus": 0.0, "plusMinusPoints": 0.0, "points": 0, "pointsFastBreak": 0, "pointsInThePaint": 0, "pointsSecondChance": 0, "reboundsDefensive": 0, "reboundsOffensive": 0, "reboundsTotal": 0, "steals": 0, "threePointersAttempted": 0, "threePointersMade": 0, "threePointersPercentage": 0.0, "turnovers": 0, "twoPointersAttempted": 0, "twoPointersMade": 0, "twoPointersPercentage": 0.0}, "name": "Richaun Holmes", "nameI": "R. Holmes", "firstName": "Richaun", "familyName": "Holmes"}, {"status": "INACTIVE", "notPlayingReason": "INACTIVE_INJURY", "notPlayingDescription": "Left Thumb; Surgery", "order": 16, "personId": 1630557, "jerseyNum": "24", "starter": "0", "oncourt": "0", "played": "0", "statistics": {"assists": 0, "blocks": 0, "blocksReceived": 0, "fieldGoalsAttempted": 0, "fieldGoalsMade": 0, "fieldGoalsPercentage": 0.0, "foulsOffensive": 0, "foulsDrawn": 0, "foulsPersonal": 0, "foulsTechnical": 0, "freeThrowsAttempted": 0, "freeThrowsMade": 0, "freeThrowsPercentage": 0.0, "minus": 0.0, "minutes": "PT00M00.00S", "minutesCalculated": "PT00M", "plus": 0.0, "plusMinusPoints": 0.0, "points": 0, "pointsFastBreak": 0, "pointsInThePaint": 0, "pointsSecondChance": 0, "reboundsDefensive": 0, "reboundsOffensive": 0, "reboundsTotal": 0, "steals": 0, "threePointersAttempted": 0, "threePointersMade": 0, "threePointersPercentage": 0.0, "turnovers": 0, "twoPointersAttempted": 0, "twoPointersMade": 0, "twoPointersPercentage": 0.0}, "name": "Corey Kispert", "nameI": "C. Kispert", "firstName": "Corey", "familyName": "Kispert"}, {"status": "INACTIVE", "notPlayingReason": "INACTIVE_INJURY", "notPlayingDescription": "Right Knee; Contusion", "order": 17, "personId": 203114, "jerseyNum": "32", "starter": "0", "oncourt": "0", "played": "0", "statistics": {"assists": 0, "blocks": 0, "blocksReceived": 0, "fieldGoalsAttempted": 0, "fieldGoalsMade": 0, "fieldGoalsPercentage": 0.0, "foulsOffensive": 0, "foulsDrawn": 0, "foulsPersonal": 0, "foulsTechnical": 0, "freeThrowsAttempted": 0, "freeThrowsMade": 0, "freeThrowsPercentage": 0.0, "minus": 0.0, "minutes": "PT00M00.00S", "minutesCalculated": "PT00M", "plus": 0.0, "plusMinusPoints": 0.0, "points": 0, "pointsFastBreak": 0, "pointsInThePaint": 0, "pointsSecondChance": 0, "reboundsDefensive": 0, "reboundsOffensive": 0, "reboundsTotal": 0, "steals": 0, "threePointersAttempted": 0, "threePointersMade": 0, "threePointersPercentage": 0.0, "turnovers": 0, "twoPointersAttempted": 0, "twoPointersMade": 0, "twoPointersPercentage": 0.0}, "name": "Khris Middleton", "nameI": "K. Middleton", "firstName": "Khris", "familyName": "Middleton"}, {"status": "INACTIVE", "notPlayingReason": "INACTIVE_INJURY", "notPlayingDescription": "Right Elbow; Contusion, Injury Management ", "order": 18, "personId": 1629673, "jerseyNum": "13", "starter": "0", "oncourt": "0", "played": "0", "statistics": {"assists": 0, "blocks": 0, "blocksReceived": 0, "fieldGoalsAttempted": 0, "fieldGoalsMade": 0, "fieldGoalsPercentage": 0.0, "foulsOffensive": 0, "foulsDrawn": 0, "foulsPersonal": 0, "foulsTechnical": 0, "freeThrowsAttempted": 0, "freeThrowsMade": 0, "freeThrowsPercentage": 0.0, "minus": 0.0, "minutes": "PT00M00.00S", "minutesCalculated": "PT00M", "plus": 0.0, "plusMinusPoints": 0.0, "points": 0, "pointsFastBreak": 0, "pointsInThePaint": 0, "pointsSecondChance": 0, "reboundsDefensive": 0, "reboundsOffensive": 0, "reboundsTotal": 0, "steals": 0, "threePointersAttempted": 0, "threePointersMade": 0, "threePointersPercentage": 0.0, "turnovers": 0, "twoPointersAttempted": 0, "twoPointersMade": 0, "twoPointersPercentage": 0.0}, "name": "Jordan Poole", "nameI": "J. Poole", "firstName": "Jordan", "familyName": "Poole"}], "statistics": {"assists": 16, "assistsTurnoverRatio": 1.23076923076923, "benchPoints": 24, "biggestLead": 3, "biggestLeadScore": "0-3", "biggestScoringRun": 13, "biggestScoringRunScore": "47-33", "blocks": 3, "blocksReceived": 8, "fastBreakPointsAttempted": 10, "fastBreakPointsMade": 4, "fastBreakPointsPercentage": 0.4, "fieldGoalsAttempted": 85, "fieldGoalsEffectiveAdjusted": 0.517647058823529, "fieldGoalsMade": 38, "fieldGoalsPercentage": 0.447058823529412, "foulsOffensive": 3, "foulsDrawn": 12, "foulsPersonal": 20, "foulsTeam": 17, "foulsTechnical": 0, "foulsTeamTechnical": 1, "freeThrowsAttempted": 11, "freeThrowsMade": 9, "freeThrowsPercentage": 0.818181818181818, "leadChanges": 5, "minutes": "PT240M00.00S", "minutesCalculated": "PT240M", "points": 97, "pointsAgainst": 109, "pointsFastBreak": 8, "pointsFromTurnovers": 14, "pointsInThePaint": 40, "pointsInThePaintAttempted": 44, "pointsInThePaintMade": 20, "pointsInThePaintPercentage": 0.45454545454545503, "pointsSecondChance": 11, "reboundsDefensive": 30, "reboundsOffensive": 8, "reboundsPersonal": 38, "reboundsTeam": 7, "reboundsTeamDefensive": 0, "reboundsTeamOffensive": 7, "reboundsTotal": 45, "secondChancePointsAttempted": 12, "secondChancePointsMade": 5, "secondChancePointsPercentage": 0.416666666666667, "steals": 4, "teamFieldGoalAttempts": 0, "threePointersAttempted": 30, "threePointersMade": 12, "threePointersPercentage": 0.4, "timeLeading": "PT03M17.00S", "timesTied": 2, "trueShootingAttempts": 89.84, "trueShootingPercentage": 0.539848619768477, "turnovers": 13, "turnoversTeam": 0, "turnoversTotal": 13, "twoPointersAttempted": 55, "twoPointersMade": 26, "twoPointersPercentage": 0.472727272727273}}, "awayTeam": {"teamId": 1610612753, "teamName": "Magic", "teamCity": "Orlando", "teamTricode": "ORL", "score": 109, "inBonus": "0", "timeoutsRemaining": 1, "periods": [{"period": 1, "periodType": "REGULAR", "score": 32}, {"period": 2, "periodType": "REGULAR", "score": 29}, {"period": 3, "periodType": "REGULAR", "score": 20}, {"period": 4, "periodType": "REGULAR", "score": 28}], "players": [{"status": "ACTIVE", "order": 1, "personId": 1630532, "jerseyNum": "22", "position": "SF", "starter": "1", "oncourt": "1", "played": "1", "statistics": {"assists": 5, "blocks": 0, "blocksReceived": 1, "fieldGoalsAttempted": 19, "fieldGoalsMade": 10, "fieldGoalsPercentage": 0.5263157894736841, "foulsOffensive": 0, "foulsDrawn": 3, "foulsPersonal": 0, "foulsTechnical": 0, "freeThrowsAttempted": 4, "freeThrowsMade": 4, "freeThrowsPercentage": 1.0, "minus": 70.0, "minutes": "PT33M56.00S", "minutesCalculated": "PT34M", "plus": 84.0, "plusMinusPoints": 14.0, "points": 27, "pointsFastBreak": 6, "pointsInThePaint": 14, "pointsSecondChance": 0, "reboundsDefensive": 5, "reboundsOffensive": 0, "reboundsTotal": 5, "steals": 1, "threePointersAttempted": 7, "threePointersMade": 3, "threePointersPercentage": 0.428571428571429, "turnovers": 1, "twoPointersAttempted": 12, "twoPointersMade": 7, "twoPointersPercentage": 0.583333333333333}, "name": "Franz Wagner", "nameI": "F. Wagner", "firstName": "Franz", "familyName": "Wagner"}, {"status": "ACTIVE", "order": 2, "personId": 1631094, "jerseyNum": "5", "position": "PF", "starter": "1", "oncourt": "1", "played": "1", "statistics": {"assists": 8, "blocks": 1, "blocksReceived": 1, "fieldGoalsAttempted": 24, "fieldGoalsMade": 11, "fieldGoalsPercentage": 0.458333333333333, "foulsOffensive": 0, "foulsDrawn": 7, "foulsPersonal": 0, "foulsTechnical": 0, "freeThrowsAttempted": 10, "freeThrowsMade": 8, "freeThrowsPercentage": 0.8, "minus": 85.0, "minutes": "PT38M57.00S", "minutesCalculated": "PT39M", "plus": 92.0, "plusMinusPoints": 7.0, "points": 33, "pointsFastBreak": 2, "pointsInThePaint": 16, "pointsSecondChance": 6, "reboundsDefensive": 15, "reboundsOffensive": 3, "reboundsTotal": 18, "steals": 0, "threePointersAttempted": 5, "threePointersMade": 3, "threePointersPercentage": 0.6, "turnovers": 4, "twoPointersAttempted": 19, "twoPointersMade": 8, "twoPointersPercentage": 0.42105263157894696}, "name": "Paolo Banchero", "nameI": "P. Banchero", "firstName": "Paolo", "familyName": "Banchero"}, {"status": "ACTIVE", "order": 3, "personId": 1628976, "jerseyNum": "34", "position": "C", "starter": "1", "oncourt": "1", "played": "1", "statistics": {"assists": 2, "blocks": 0, "blocksReceived": 1, "fieldGoalsAttempted": 9, "fieldGoalsMade": 5, "fieldGoalsPercentage": 0.555555555555556, "foulsOffensive": 0, "foulsDrawn": 0, "foulsPersonal": 3, "foulsTechnical": 0, "freeThrowsAttempted": 0, "freeThrowsMade": 0, "freeThrowsPercentage": 0.0, "minus": 71.0, "minutes": "PT30M06.00S", "minutesCalculated": "PT30M", "plus": 67.0, "plusMinusPoints": -4.0, "points": 10, "pointsFastBreak": 0, "pointsInThePaint": 10, "pointsSecondChance": 2, "reboundsDefensive": 3, "reboundsOffensive": 4, "reboundsTotal": 7, "steals": 0, "threePointersAttempted": 2, "threePointersMade": 0, "threePointersPercentage": 0.0, "turnovers": 0, "twoPointersAttempted": 7, "twoPointersMade": 5, "twoPointersPercentage": 0.714285714285714}, "name": "Wendell Carter Jr.", "nameI": "W. Carter Jr.", "firstName": "Wendell", "familyName": "Carter Jr."}, {"status": "ACTIVE", "order": 4, "personId": 203484, "jerseyNum": "3", "position": "SG", "starter": "1", "oncourt": "1", "played": "1", "statistics": {"assists": 5, "blocks": 1, "blocksReceived": 0, "fieldGoalsAttempted": 4, "fieldGoalsMade": 3, "fieldGoalsPercentage": 0.75, "foulsOffensive": 0, "foulsDrawn": 4, "foulsPersonal": 1, "foulsTechnical": 0, "freeThrowsAttempted": 6, "freeThrowsMade": 6, "freeThrowsPercentage": 1.0, "minus": 73.0, "minutes": "PT32M51.00S", "minutesCalculated": "PT33M", "plus": 78.0, "plusMinusPoints": 5.0, "points": 13, "pointsFastBreak": 2, "pointsInThePaint": 0, "pointsSecondChance": 0, "reboundsDefensive": 3, "reboundsOffensive": 0, "reboundsTotal": 3, "steals": 2, "threePointersAttempted": 2, "threePointersMade": 1, "threePointersPercentage": 0.5, "turnovers": 1, "twoPointersAttempted": 2, "twoPointersMade": 2, "twoPointersPercentage": 1.0}, "name": "Kentavious Caldwell-Pope", "nameI": "K. Caldwell-Pope", "firstName": "Kentavious", "familyName": "Caldwell-Pope"}, {"status": "ACTIVE", "order": 5, "personId": 202709, "jerseyNum": "10", "position": "PG", "starter": "1", "oncourt": "1", "played": "1", "statistics": {"assists": 1, "blocks": 0, "blocksReceived": 0, "fieldGoalsAttempted": 6, "fieldGoalsMade": 3, "fieldGoalsPercentage": 0.5, "foulsOffensive": 0, "foulsDrawn": 1, "foulsPersonal": 1, "foulsTechnical": 0, "freeThrowsAttempted": 0, "freeThrowsMade": 0, "freeThrowsPercentage": 0.0, "minus": 59.0, "minutes": "PT25M19.00S", "minutesCalculated": "PT25M", "plus": 59.0, "plusMinusPoints": 0.0, "points": 8, "pointsFastBreak": 3, "pointsInThePaint": 2, "pointsSecondChance": 0, "reboundsDefensive": 2, "reboundsOffensive": 0, "reboundsTotal": 2, "steals": 1, "threePointersAttempted": 5, "threePointersMade": 2, "threePointersPercentage": 0.4, "turnovers": 0, "twoPointersAttempted": 1, "twoPointersMade": 1, "twoPointersPercentage": 1.0}, "name": "Cory Joseph", "nameI": "C. Joseph", "firstName": "Cory", "familyName": "Joseph"}, {"status": "ACTIVE", "order": 6, "personId": 1641710, "jerseyNum": "0", "starter": "0", "oncourt": "0", "played": "1", "statistics": {"assists": 4, "blocks": 2, "blocksReceived": 0, "fieldGoalsAttempted": 10, "fieldGoalsMade": 3, "fieldGoalsPercentage": 0.3, "foulsOffensive": 0, "foulsDrawn": 2, "foulsPersonal": 2, "foulsTechnical": 0, "freeThrowsAttempted": 1, "freeThrowsMade": 0, "freeThrowsPercentage": 0.0, "minus": 38.0, "minutes": "PT22M41.00S", "minutesCalculated": "PT23M", "plus": 50.0, "plusMinusPoints": 12.0, "points": 6, "pointsFastBreak": 0, "pointsInThePaint": 6, "pointsSecondChance": 2, "reboundsDefensive": 2, "reboundsOffensive": 1, "reboundsTotal": 3, "steals": 1, "threePointersAttempted": 3, "threePointersMade": 0, "threePointersPercentage": 0.0, "turnovers": 0, "twoPointersAttempted": 7, "twoPointersMade": 3, "twoPointersPercentage": 0.428571428571429}, "name": "Anthony Black", "nameI": "A. Black", "firstName": "Anthony", "familyName": "Black"}, {"status": "ACTIVE", "order": 7, "personId": 203914, "jerseyNum": "14", "starter": "0", "oncourt": "0", "played": "1", "statistics": {"assists": 1, "blocks": 1, "blocksReceived": 0, "fieldGoalsAttempted": 0, "fieldGoalsMade": 0, "fieldGoalsPercentage": 0.0, "foulsOffensive": 0, "foulsDrawn": 0, "foulsPersonal": 3, "foulsTechnical": 0, "freeThrowsAttempted": 0, "freeThrowsMade": 0, "freeThrowsPercentage": 0.0, "minus": 24.0, "minutes": "PT15M09.00S", "minutesCalculated": "PT15M", "plus": 31.0, "plusMinusPoints": 7.0, "points": 0, "pointsFastBreak": 0, "pointsInThePaint": 0, "pointsSecondChance": 0, "reboundsDefensive": 1, "reboundsOffensive": 1, "reboundsTotal": 2, "steals": 0, "threePointersAttempted": 0, "threePointersMade": 0, "threePointersPercentage": 0.0, "turnovers": 1, "twoPointersAttempted": 0, "twoPointersMade": 0, "twoPointersPercentage": 0.0}, "name": "Gary Harris", "nameI": "G. Harris", "firstName": "Gary", "familyName": "Harris"}, {"status": "ACTIVE", "order": 8, "personId": 1630175, "jerseyNum": "50", "starter": "0", "oncourt": "0", "played": "1", "statistics": {"assists": 0, "blocks": 1, "blocksReceived": 0, "fieldGoalsAttempted": 5, "fieldGoalsMade": 2, "fieldGoalsPercentage": 0.4, "foulsOffensive": 0, "foulsDrawn": 1, "foulsPersonal": 1, "foulsTechnical": 0, "freeThrowsAttempted": 2, "freeThrowsMade": 2, "freeThrowsPercentage": 1.0, "minus": 27.0, "minutes": "PT14M04.00S", "minutesCalculated": "PT14M", "plus": 25.0, "plusMinusPoints": -2.0, "points": 8, "pointsFastBreak": 0, "pointsInThePaint": 0, "pointsSecondChance": 3, "reboundsDefensive": 1, "reboundsOffensive": 0, "reboundsTotal": 1, "steals": 0, "threePointersAttempted": 5, "threePointersMade": 2, "threePointersPercentage": 0.4, "turnovers": 0, "twoPointersAttempted": 0, "twoPointersMade": 0, "twoPointersPercentage": 0.0}, "name": "Cole Anthony", "nameI": "C. Anthony", "firstName": "Cole", "familyName": "Anthony"}, {"status": "ACTIVE", "order": 9, "personId": 1628371, "jerseyNum": "1", "starter": "0", "oncourt": "0", "played": "1", "statistics": {"assists": 1, "blocks": 2, "blocksReceived": 0, "fieldGoalsAttempted": 4, "fieldGoalsMade": 1, "fieldGoalsPercentage": 0.25, "foulsOffensive": 0, "foulsDrawn": 1, "foulsPersonal": 0, "foulsTechnical": 0, "freeThrowsAttempted": 2, "freeThrowsMade": 2, "freeThrowsPercentage": 1.0, "minus": 18.0, "minutes": "PT13M36.00S", "minutesCalculated": "PT14M", "plus": 28.0, "plusMinusPoints": 10.0, "points": 4, "pointsFastBreak": 0, "pointsInThePaint": 2, "pointsSecondChance": 2, "reboundsDefensive": 1, "reboundsOffensive": 3, "reboundsTotal": 4, "steals": 2, "threePointersAttempted": 0, "threePointersMade": 0, "threePointersPercentage": 0.0, "turnovers": 1, "twoPointersAttempted": 4, "twoPointersMade": 1, "twoPointersPercentage": 0.25}, "name": "Jonathan Isaac", "nameI": "J. Isaac", "firstName": "Jonathan", "familyName": "Isaac"}, {"status": "ACTIVE", "order": 10, "personId": 1631216, "jerseyNum": "2", "starter": "0", "oncourt": "0", "played": "1", "statistics": {"assists": 0, "blocks": 0, "blocksReceived": 0, "fieldGoalsAttempted": 1, "fieldGoalsMade": 0, "fieldGoalsPercentage": 0.0, "foulsOffensive": 0, "foulsDrawn": 1, "foulsPersonal": 1, "foulsTechnical": 0, "freeThrowsAttempted": 0, "freeThrowsMade": 0, "freeThrowsPercentage": 0.0, "minus": 16.0, "minutes": "PT10M49.00S", "minutesCalculated": "PT11M", "plus": 23.0, "plusMinusPoints": 7.0, "points": 0, "pointsFastBreak": 0, "pointsInThePaint": 0, "pointsSecondChance": 0, "reboundsDefensive": 1, "reboundsOffensive": 1, "reboundsTotal": 2, "steals": 0, "threePointersAttempted": 1, "threePointersMade": 0, "threePointersPercentage": 0.0, "turnovers": 0, "twoPointersAttempted": 0, "twoPointersMade": 0, "twoPointersPercentage": 0.0}, "name": "Caleb Houstan", "nameI": "C. Houstan", "firstName": "Caleb", "familyName": "Houstan"}, {"status": "ACTIVE", "order": 11, "personId": 1629048, "jerseyNum": "35", "starter": "0", "oncourt": "0", "played": "1", "statistics": {"assists": 0, "blocks": 0, "blocksReceived": 0, "fieldGoalsAttempted": 0, "fieldGoalsMade": 0, "fieldGoalsPercentage": 0.0, "foulsOffensive": 0, "foulsDrawn": 0, "foulsPersonal": 0, "foulsTechnical": 0, "freeThrowsAttempted": 0, "freeThrowsMade": 0, "freeThrowsPercentage": 0.0, "minus": 4.0, "minutes": "PT02M32.00S", "minutesCalculated": "PT02M", "plus": 8.0, "plusMinusPoints": 4.0, "points": 0, "pointsFastBreak": 0, "pointsInThePaint": 0, "pointsSecondChance": 0, "reboundsDefensive": 0, "reboundsOffensive": 0, "reboundsTotal": 0, "steals": 0, "threePointersAttempted": 0, "threePointersMade": 0, "threePointersPercentage": 0.0, "turnovers": 0, "twoPointersAttempted": 0, "twoPointersMade": 0, "twoPointersPercentage": 0.0}, "name": "Goga Bitadze", "nameI": "G. Bitadze", "firstName": "Goga", "familyName": "Bitadze"}, {"status": "ACTIVE", "order": 12, "personId": 1641783, "jerseyNum": "23", "starter": "0", "oncourt": "0", "played": "0", "statistics": {"assists": 0, "blocks": 0, "blocksReceived": 0, "fieldGoalsAttempted": 0, "fieldGoalsMade": 0, "fieldGoalsPercentage": 0.0, "foulsOffensive": 0, "foulsDrawn": 0, "foulsPersonal": 0, "foulsTechnical": 0, "freeThrowsAttempted": 0, "freeThrowsMade": 0, "freeThrowsPercentage": 0.0, "minus": 0.0, "minutes": "PT00M00.00S", "minutesCalculated": "PT00M", "plus": 0.0, "plusMinusPoints": 0.0, "points": 0, "pointsFastBreak": 0, "pointsInThePaint": 0, "pointsSecondChance": 0, "reboundsDefensive": 0, "reboundsOffensive": 0, "reboundsTotal": 0, "steals": 0, "threePointersAttempted": 0, "threePointersMade": 0, "threePointersPercentage": 0.0, "turnovers": 0, "twoPointersAttempted": 0, "twoPointersMade": 0, "twoPointersPercentage": 0.0}, "name": "Tristan da Silva", "nameI": "T. da Silva", "firstName": "Tristan", "familyName": "da Silva"}, {"status": "ACTIVE", "order": 13, "personId": 1641724, "jerseyNum": "13", "starter": "0", "oncourt": "0", "played": "0", "statistics": {"assists": 0, "blocks": 0, "blocksReceived": 0, "fieldGoalsAttempted": 0, "fieldGoalsMade": 0, "fieldGoalsPercentage": 0.0, "foulsOffensive": 0, "foulsDrawn": 0, "foulsPersonal": 0, "foulsTechnical": 0, "freeThrowsAttempted": 0, "freeThrowsMade": 0, "freeThrowsPercentage": 0.0, "minus": 0.0, "minutes": "PT00M00.00S", "minutesCalculated": "PT00M", "plus": 0.0, "plusMinusPoints": 0.0, "points": 0, "pointsFastBreak": 0, "pointsInThePaint": 0, "pointsSecondChance": 0, "reboundsDefensive": 0, "reboundsOffensive": 0, "reboundsTotal": 0, "steals": 0, "threePointersAttempted": 0, "threePointersMade": 0, "threePointersPercentage": 0.0, "turnovers": 0, "twoPointersAttempted": 0, "twoPointersMade": 0, "twoPointersPercentage": 0.0}, "name": "Jett Howard", "nameI": "J. Howard", "firstName": "Jett", "familyName": "Howard"}, {"status": "ACTIVE", "order": 14, "personId": 1630243, "jerseyNum": "12", "starter": "0", "oncourt": "0", "played": "0", "statistics": {"assists": 0, "blocks": 0, "blocksReceived": 0, "fieldGoalsAttempted": 0, "fieldGoalsMade": 0, "fieldGoalsPercentage": 0.0, "foulsOffensive": 0, "foulsDrawn": 0, "foulsPersonal": 0, "foulsTechnical": 0, "freeThrowsAttempted": 0, "freeThrowsMade": 0, "freeThrowsPercentage": 0.0, "minus": 0.0, "minutes": "PT00M00.00S", "minutesCalculated": "PT00M", "plus": 0.0, "plusMinusPoints": 0.0, "points": 0, "pointsFastBreak": 0, "pointsInThePaint": 0, "pointsSecondChance": 0, "reboundsDefensive": 0, "reboundsOffensive": 0, "reboundsTotal": 0, "steals": 0, "threePointersAttempted": 0, "threePointersMade": 0, "threePointersPercentage": 0.0, "turnovers": 0, "twoPointersAttempted": 0, "twoPointersMade": 0, "twoPointersPercentage": 0.0}, "name": "Trevelin Queen", "nameI": "T. Queen", "firstName": "Trevelin", "familyName": "Queen"}, {"status": "INACTIVE", "notPlayingReason": "INACTIVE_GLEAGUE_TWOWAY", "order": 15, "personId": 1630644, "jerseyNum": "8", "starter": "0", "oncourt": "0", "played": "0", "statistics": {"assists": 0, "blocks": 0, "blocksReceived": 0, "fieldGoalsAttempted": 0, "fieldGoalsMade": 0, "fieldGoalsPercentage": 0.0, "foulsOffensive": 0, "foulsDrawn": 0, "foulsPersonal": 0, "foulsTechnical": 0, "freeThrowsAttempted": 0, "freeThrowsMade": 0, "freeThrowsPercentage": 0.0, "minus": 0.0, "minutes": "PT00M00.00S", "minutesCalculated": "PT00M", "plus": 0.0, "plusMinusPoints": 0.0, "points": 0, "pointsFastBreak": 0, "pointsInThePaint": 0, "pointsSecondChance": 0, "reboundsDefensive": 0, "reboundsOffensive": 0, "reboundsTotal": 0, "steals": 0, "threePointersAttempted": 0, "threePointersMade": 0, "threePointersPercentage": 0.0, "turnovers": 0, "twoPointersAttempted": 0, "twoPointersMade": 0, "twoPointersPercentage": 0.0}, "name": "Mac McClung", "nameI": "M. McClung", "firstName": "Mac", "familyName": "McClung"}, {"status": "INACTIVE", "notPlayingReason": "INACTIVE_INJURY", "notPlayingDescription": "Left Knee; Trochlea Cartilage Tear", "order": 16, "personId": 1630591, "jerseyNum": "4", "starter": "0", "oncourt": "0", "played": "0", "statistics": {"assists": 0, "blocks": 0, "blocksReceived": 0, "fieldGoalsAttempted": 0, "fieldGoalsMade": 0, "fieldGoalsPercentage": 0.0, "foulsOffensive": 0, "foulsDrawn": 0, "foulsPersonal": 0, "foulsTechnical": 0, "freeThrowsAttempted": 0, "freeThrowsMade": 0, "freeThrowsPercentage": 0.0, "minus": 0.0, "minutes": "PT00M00.00S", "minutesCalculated": "PT00M", "plus": 0.0, "plusMinusPoints": 0.0, "points": 0, "pointsFastBreak": 0, "pointsInThePaint": 0, "pointsSecondChance": 0, "reboundsDefensive": 0, "reboundsOffensive": 0, "reboundsTotal": 0, "steals": 0, "threePointersAttempted": 0, "threePointersMade": 0, "threePointersPercentage": 0.0, "turnovers": 0, "twoPointersAttempted": 0, "twoPointersMade": 0, "twoPointersPercentage": 0.0}, "name": "Jalen Suggs", "nameI": "J. Suggs", "firstName": "Jalen", "familyName": "Suggs"}, {"status": "INACTIVE", "notPlayingReason": "INACTIVE_GLEAGUE_TWOWAY", "order": 17, "personId": 1630679, "jerseyNum": "55", "starter": "0", "oncourt": "0", "played": "0", "statistics": {"assists": 0, "blocks": 0, "blocksReceived": 0, "fieldGoalsAttempted": 0, "fieldGoalsMade": 0, "fieldGoalsPercentage": 0.0, "foulsOffensive": 0, "foulsDrawn": 0, "foulsPersonal": 0, "foulsTechnical": 0, "freeThrowsAttempted": 0, "freeThrowsMade": 0, "freeThrowsPercentage": 0.0, "minus": 0.0, "minutes": "PT00M00.00S", "minutesCalculated": "PT00M", "plus": 0.0, "plusMinusPoints": 0.0, "points": 0, "pointsFastBreak": 0, "pointsInThePaint": 0, "pointsSecondChance": 0, "reboundsDefensive": 0, "reboundsOffensive": 0, "reboundsTotal": 0, "steals": 0, "threePointersAttempted": 0, "threePointersMade": 0, "threePointersPercentage": 0.0, "turnovers": 0, "twoPointersAttempted": 0, "twoPointersMade": 0, "twoPointersPercentage": 0.0}, "name": "Ethan Thompson", "nameI": "E. Thompson", "firstName": "Ethan", "familyName": "Thompson"}, {"status": "INACTIVE", "notPlayingReason": "INACTIVE_INJURY", "notPlayingDescription": "Left Knee; Torn ACL", "order": 18, "personId": 1629021, "jerseyNum": "21", "starter": "0", "oncourt": "0", "played": "0", "statistics": {"assists": 0, "blocks": 0, "blocksReceived": 0, "fieldGoalsAttempted": 0, "fieldGoalsMade": 0, "fieldGoalsPercentage": 0.0, "foulsOffensive": 0, "foulsDrawn": 0, "foulsPersonal": 0, "foulsTechnical": 0, "freeThrowsAttempted": 0, "freeThrowsMade": 0, "freeThrowsPercentage": 0.0, "minus": 0.0, "minutes": "PT00M00.00S", "minutesCalculated": "PT00M", "plus": 0.0, "plusMinusPoints": 0.0, "points": 0, "pointsFastBreak": 0, "pointsInThePaint": 0, "pointsSecondChance": 0, "reboundsDefensive": 0, "reboundsOffensive": 0, "reboundsTotal": 0, "steals": 0, "threePointersAttempted": 0, "threePointersMade": 0, "threePointersPercentage": 0.0, "turnovers": 0, "twoPointersAttempted": 0, "twoPointersMade": 0, "twoPointersPercentage": 0.0}, "name": "Moritz Wagner", "nameI": "M. Wagner", "firstName": "Moritz", "familyName": "Wagner"}], "statistics": {"assists": 27, "assistsTurnoverRatio": 2.25, "benchPoints": 18, "biggestLead": 19, "biggestLeadScore": "72-53", "biggestScoringRun": 13, "biggestScoringRunScore": "47-33", "blocks": 8, "blocksReceived": 3, "fastBreakPointsAttempted": 5, "fastBreakPointsMade": 4, "fastBreakPointsPercentage": 0.8, "fieldGoalsAttempted": 82, "fieldGoalsEffectiveAdjusted": 0.530487804878049, "fieldGoalsMade": 38, "fieldGoalsPercentage": 0.463414634146342, "foulsOffensive": 0, "foulsDrawn": 20, "foulsPersonal": 12, "foulsTeam": 12, "foulsTechnical": 0, "foulsTeamTechnical": 1, "freeThrowsAttempted": 25, "freeThrowsMade": 22, "freeThrowsPercentage": 0.88, "leadChanges": 5, "minutes": "PT240M00.00S", "minutesCalculated": "PT240M", "points": 109, "pointsAgainst": 97, "pointsFastBreak": 13, "pointsFromTurnovers": 18, "pointsInThePaint": 50, "pointsInThePaintAttempted": 43, "pointsInThePaintMade": 25, "pointsInThePaintPercentage": 0.581395348837209, "pointsSecondChance": 15, "reboundsDefensive": 34, "reboundsOffensive": 13, "reboundsPersonal": 47, "reboundsTeam": 4, "reboundsTeamDefensive": 0, "reboundsTeamOffensive": 4, "reboundsTotal": 51, "secondChancePointsAttempted": 14, "secondChancePointsMade": 6, "secondChancePointsPercentage": 0.428571428571429, "steals": 7, "teamFieldGoalAttempts": 0, "threePointersAttempted": 30, "threePointersMade": 11, "threePointersPercentage": 0.366666666666667, "timeLeading": "PT43M52.00S", "timesTied": 2, "trueShootingAttempts": 93.0, "trueShootingPercentage": 0.586021505376344, "turnovers": 8, "turnoversTeam": 4, "turnoversTotal": 12, "twoPointersAttempted": 52, "twoPointersMade": 27, "twoPointersPercentage": 0.5192307692307689}}}